{
  "conflict_sources": [
    {
      "file_path": "services/surfaceflinger/SurfaceFlinger.cpp",
      "merged_line_count": 8920,
      "mergebot_line_count": 7949,
      "diff_line_count": 2891
    },
    {
      "file_path": "services/surfaceflinger/WindowInfosListenerInvoker.cpp",
      "merged_line_count": 149,
      "mergebot_line_count": 173,
      "diff_line_count": 21
    },
    {
      "file_path": "services/surfaceflinger/WindowInfosListenerInvoker.h",
      "merged_line_count": 62,
      "mergebot_line_count": 64,
      "diff_line_count": 9
    }
  ],
  "total_diff_line_count": 2921,
  "total_merged_line_count": 9131,
  "total_mergebot_line_count": 8186,
  "precision": 0.6431712680185683,
  "recall": 0.5766071624137553
}