{
    "conflict_sources": [
        {
            "file_path": "tools/pythonpkg/duckdb_python.cpp",
            "merged_line_count": 309,
            "raw_conflict_line_count": 287,
            "diff_line_count": 6
        },
        {
            "file_path": "tools/pythonpkg/src/include/duckdb_python/connection_wrapper.hpp",
            "merged_line_count": 180,
            "raw_conflict_line_count": 131,
            "diff_line_count": 8
        },
        {
            "file_path": "tools/pythonpkg/src/pyrelation.cpp",
            "merged_line_count": 925,
            "raw_conflict_line_count": 803,
            "diff_line_count": 6
        },
        {
            "file_path": "tools/pythonpkg/src/python_import_cache.cpp",
            "merged_line_count": 68,
            "raw_conflict_line_count": 58,
            "diff_line_count": 8
        }
    ],
    "total_diff_line_count": 28,
    "total_merged_line_count": 1482,
    "total_raw_conflict_line_count": 1279,
    "precision": 0.9781078967943706,
    "recall": 0.8441295546558705
}