[
  {
    "code": [
      "Status MakeRoomForWrite(ColumnFamilyData* cfd,",
      "                          bool force /* flush even if there is room? */);",
      "// closed whenever DB mutex is released.",
      "Status MakeRoomForWrite(bool force /* compact even if there is room? */,",
      "                          SuperVersion** superversion_to_free,",
      "                          log::Writer** old_log);"
    ],
    "label": "",
    "index": 0,
    "confidence": 0.5,
    "desc": "Declarations merge."
  }
]