{
    "conflict_sources": [
        {
            "file_path": "odrefresh/odr_config.h",
            "merged_line_count": 233,
            "raw_conflict_line_count": 193,
            "diff_line_count": 23
        },
        {
            "file_path": "odrefresh/odrefresh.cc",
            "merged_line_count": 1734,
            "raw_conflict_line_count": 1859,
            "diff_line_count": 482
        }
    ],
    "total_diff_line_count": 505,
    "total_merged_line_count": 1967,
    "total_raw_conflict_line_count": 2052,
    "precision": 0.7538986354775828,
    "recall": 0.7864768683274022
}