[
    {
        "a_contents": "    void initSaveAfterCopy();",
        "b_contents": "    void initCopyAndCloseAfterUpload();",
        "base_contents": "",
        "res_region": "    void initCopyAndCloseAfterUpload();\n    void initSaveAfterCopy();",
        "lookback": "    void initConfingButtons();\n    void initAutostart();\n    void initCloseAfterCapture();",
        "lookahead": "};",
        "label": [
            "concat",
            "complex_conflict"
        ],
        "start_line": 68,
        "end_line": 73,
        "merge_gen_region": "void initSaveAfterCopy(); void initCopyAndCloseAfterUpload();",
        "resolved": false
    }
]