{
    "conflict_sources": [
        {
            "file_path": "services/camera/libcameraservice/CameraService.cpp",
            "merged_line_count": 6640,
            "mergegen_conflict_line_count": 5275,
            "diff_line_count": 62
        },
        {
            "file_path": "services/camera/libcameraservice/CameraService.h",
            "merged_line_count": 1619,
            "mergegen_conflict_line_count": 782,
            "diff_line_count": 28
        },
        {
            "file_path": "services/camera/libcameraservice/common/Camera2ClientBase.cpp",
            "merged_line_count": 535,
            "mergegen_conflict_line_count": 409,
            "diff_line_count": 1
        }
    ],
    "total_diff_line_count": 91,
    "total_merged_line_count": 8794,
    "total_mergegen_conflict_line_count": 6466,
    "precision": 0.9859263841633158,
    "recall": 0.7249260859677052
}