{
  "conflict_sources": [
    {
      "file_path": "src/execution/operator/aggregate/physical_window.cpp",
      "merged_line_count": 1386,
      "mergebot_line_count": 1389,
      "diff_line_count": 23
    },
    {
      "file_path": "src/execution/operator/join/physical_hash_join.cpp",
      "merged_line_count": 910,
      "mergebot_line_count": 917,
      "diff_line_count": 42
    },
    {
      "file_path": "src/execution/operator/scan/physical_column_data_scan.cpp",
      "merged_line_count": 77,
      "mergebot_line_count": 79,
      "diff_line_count": 1
    },
    {
      "file_path": "src/include/duckdb/main/client_config.hpp",
      "merged_line_count": 123,
      "mergebot_line_count": 123,
      "diff_line_count": 2
    },
    {
      "file_path": "src/parallel/pipeline_executor.cpp",
      "merged_line_count": 522,
      "mergebot_line_count": 585,
      "diff_line_count": 158
    }
  ],
  "total_diff_line_count": 226,
  "total_merged_line_count": 3018,
  "total_mergebot_line_count": 3093,
  "precision": 0.9269317814419658,
  "recall": 0.9499668654738237
}